.gitignore
.pylintrc
.yapfignore
LICENSE
MANIFEST.in
README.rst
THIRD-PARTY-NOTICES
setup.cfg
setup.py
tests/__init__.py
tests/context.py
tests/mark.py
tests/test_file_stdlib.py
tests/test_flags.py
tests/test_io_stdlib.py
tests/test_winnan.py
winnan/.gitignore
winnan/__init__.py
winnan/_version.py
winnan/flags.py
winnan/io_shim.py
winnan/os_shim.py
winnan.egg-info/PKG-INFO
winnan.egg-info/SOURCES.txt
winnan.egg-info/dependency_links.txt
winnan.egg-info/not-zip-safe
winnan.egg-info/requires.txt
winnan.egg-info/top_level.txt
winnan/_cython/.gitignore
winnan/_cython/__init__.py
winnan/_cython/fcntl.c
winnan/_cython/fcntl.pyx